src/__init__.py
src/discord_mcp_server.py
discord_mcp_server-0.1.4.dist-info/METADATA
discord_mcp_server-0.1.4.dist-info/WHEEL
discord_mcp_server-0.1.4.dist-info/entry_points.txt
discord_mcp_server-0.1.4.dist-info/RECORD
