Metadata-Version: 2.4
Name: discord-mcp-server
Version: 0.1.4
Summary: A Discord webhook server using MCP
Author-email: mabingyin <ma786074771@outlook.com>
License: MIT
Requires-Python: >=3.10
Requires-Dist: build>=1.2.2.post1
Requires-Dist: fastapi>=0.68.0
Requires-Dist: mcp[cli]>=1.6.0
Requires-Dist: pip>=25.0.1
Requires-Dist: pydantic>=2.0.0
Requires-Dist: requests>=2.31.0
Requires-Dist: twine>=6.1.0
Requires-Dist: uvicorn>=0.15.0
